Workbook

Sheet REGISTRO DE ACTIVOS NUEVOS
A1: CU-PAT — Gestión Patrimonial
A2: EMPRESA SUCHEL TROPICAL · DIRECCIÓN COMERCIAL · 39 activos · registro completo
A4: No. | B4: DIRECCION | C4: CODIGO | D4: NOMBRE AFT | E4: CATEGORIA | F4: ESTADO | G4: AREA | H4: MARCA | I4: MODELO | J4: SERIE | K4: FECHA COMPRA | L4: VALOR.CLP. | M4: RESPONSABLE
A5: 1 | B5: DIRECCION COMERCIAL | C5: DC-01 | D5: 1 EQUIPO CLIMATIZACION 12000 BTU | E5: EQUIPOS DE CLIMATIZACION Y REFRIGERACION | F5: SERVICIO | G5: OFICINA DIRECTOR COMERCIAL | H5: Midea | I5: Xtreme Save 12.000 BTU | J5: SN-DC01-2186 | K5: 44327 | L5: 389900 | M5: DIRECTOR COMERCIAL
A6: 2 | B6: DIRECCION COMERCIAL | C6: DC-02 | D6: 1 SOFA 3 PERSONAS | E6: MOBILIARIO | F6: SERVICIO | G6: OFICINA DIRECTOR COMERCIAL | H6: Rosen | I6: Milano 3 Cuerpos | J6: SN-DC02-2323 | K6: 44332 | L6: 429900 | M6: DIRECTOR COMERCIAL
A7: 3 | B7: DIRECCION COMERCIAL | C7: DC-03 | D7: BUTACA CON BRAZOS | E7: MOBILIARIO | F7: SERVICIO | G7: OFICINA DIRECTOR COMERCIAL | H7: Mica | I7: Oslo con Brazos | J7: SN-DC03-2460 | K7: 44337 | L7: 94990 | M7: DIRECTOR COMERCIAL
A8: 4 | B8: DIRECCION COMERCIAL | C8: DC-04 | D8: BUTACA CON BRAZOS | E8: MOBILIARIO | F8: SERVICIO | G8: OFICINA DIRECTOR COMERCIAL | H8: Mica | I8: Oslo con Brazos | J8: SN-DC04-2597 | K8: 44327 | L8: 94990 | M8: DIRECTOR COMERCIAL
A9: 5 | B9: DIRECCION COMERCIAL | C9: DC-05 | D9: BUTACA CON BRAZOS | E9: MOBILIARIO | F9: SERVICIO | G9: OFICINA DIRECTOR COMERCIAL | H9: Mica | I9: Oslo con Brazos | J9: SN-DC05-2734 | K9: 44332 | L9: 94990 | M9: DIRECTOR COMERCIAL
A10: 6 | B10: DIRECCION COMERCIAL | C10: DC-06 | D10: 1 TV DIGITAL LG 45" | E10: MOBILIARIO | F10: SERVICIO | G10: OFICINA DIRECTOR COMERCIAL | H10: LG | I10: 45UR7300 UHD | J10: SN-DC06-2871 | K10: 44337 | L10: 329900 | M10: DIRECTOR COMERCIAL
A11: 7 | B11: DIRECCION COMERCIAL | C11: DC-07 | D11: 1 LAPTOP | E11: INFORMATICA | F11: SERVICIO | G11: OFICINA DIRECTOR COMERCIAL | H11: Lenovo | I11: ThinkPad E14 Gen 5 | J11: SN-DC07-3008 | K11: 44327 | L11: 749900 | M11: DIRECTOR COMERCIAL
A12: 8 | B12: DIRECCION COMERCIAL | C12: DC-08 | D12: 1 BURO | E12: MOBILIARIO | F12: SERVICIO | G12: OFICINA DIRECTOR COMERCIAL | H12: Rosen | I12: Buro Ejecutivo BR-120 | J12: SN-DC08-3145 | K12: 44332 | L12: 159900 | M12: DIRECTOR COMERCIAL
A13: 9 | B13: DIRECCION COMERCIAL | C13: DC-09 | D13: 1 SILLA GIRATORIA | E13: MOBILIARIO | F13: SERVICIO | G13: OFICINA DIRECTOR COMERCIAL | H13: Ergosillas | I13: Pro Ergo 120 | J13: SN-DC09-3282 | K13: 44337 | L13: 109900 | M13: DIRECTOR COMERCIAL
A14: 10 | B14: DIRECCION COMERCIAL | C14: DC-10 | D14: 1 CREDENZA METALICA | E14: MOBILIARIO | F14: SERVICIO | G14: OFICINA DIRECTOR COMERCIAL | H14: Dimeiggs | I14: Credenza Metalica CRD-2P | J14: SN-DC10-3419 | K14: 44327 | L14: 189900 | M14: DIRECTOR COMERCIAL
A15: 11 | B15: DIRECCION COMERCIAL | C15: DC-11 | D15: 1 IMPRESORA | E15: INFORMATICA | F15: SERVICIO | G15: OFICINA DIRECTOR COMERCIAL | H15: Epson | I15: EcoTank L3250 | J15: SN-DC11-3556 | K15: 44332 | L15: 179900 | M15: DIRECTOR COMERCIAL
A16: 12 | B16: DIRECCION COMERCIAL | C16: DC-12 | D16: 1 IMPRESORA | E16: INFORMATICA | F16: SERVICIO | G16: DEPARTAMENTO VENTAS NACIONAL | H16: Epson | I16: EcoTank L3250 | J16: SN-DC12-3693 | K16: 44617 | L16: 179900 | M16: JEFE DPTO. VENTAS NACIONAL
... A43: 39 | B43: DIRECCION COMERCIAL | C43: DC-39 | D43: 1 CREDENZA METALICA | E43: MOBILIARIO | F43: SERVICIO | G43: DEPARTAMENTO VENTAS INTERNACIONAL | H43: Dimeiggs | I43: Credenza Metalica CRD-2P | J43: SN-DC39-7392 | K43: 44770 | L43: 189900 | M43: JEFE DPTO. VENTAS INTERNACIONAL
A44: TOTAL | D44: =COUNTA(C5:C43)&" activos registrados" | L44: =SUM(L5:L43)

Sheet Listas
A1: CATEGORIA | B1: ESTADO | C1: DIRECCION | D1: AREA
A2: MOBILIARIO | B2: SERVICIO | C2: DIRECCION GENERAL | D2: OFICINA DIRECTOR COMERCIAL
A3: INFORMATICA | B3: MTTO | C3: DIRECCION TECNICO-PRODUCTIVA | D3: DEPARTAMENTO VENTAS NACIONAL
A4: EQUIPOS DE CLIMATIZACION Y REFRIGERACION | B4: BAJA | C4: DIRECCION COMERCIAL | D4: DEPARTAMENTO VENTAS INTERNACIONAL
A5: ELECTRODOMESTICOS | C5: DIRECCION ECONOMIA
A6: TECNOLOGIA | C6: DIRECCION LOGISTICA
A7: TRANSPORTE

Sheet Resumen
A1: Resumen del registro
A3: Por área
A4: Área | B4: Activos | C4: Valor total | D4: % del valor
A5: OFICINA DIRECTOR COMERCIAL | B5: =COUNTIF('REGISTRO DE ACTIVOS NUEVOS'!$G$5:$G$43,$A5) | C5: =SUMIF('REGISTRO DE ACTIVOS NUEVOS'!$G$5:$G$43,$A5,'REGISTRO DE ACTIVOS NUEVOS'!$L$5:$L$43) | D5: =IFERROR(C5/SUM('REGISTRO DE ACTIVOS NUEVOS'!$L$5:$L$43),0)
A6: DEPARTAMENTO VENTAS NACIONAL | B6: =COUNTIF('REGISTRO DE ACTIVOS NUEVOS'!$G$5:$G$43,$A6) | C6: =SUMIF('REGISTRO DE ACTIVOS NUEVOS'!$G$5:$G$43,$A6,'REGISTRO DE ACTIVOS NUEVOS'!$L$5:$L$43) | D6: =IFERROR(C6/SUM('REGISTRO DE ACTIVOS NUEVOS'!$L$5:$L$43),0)
A7: DEPARTAMENTO VENTAS INTERNACIONAL | B7: =COUNTIF('REGISTRO DE ACTIVOS NUEVOS'!$G$5:$G$43,$A7) | C7: =SUMIF('REGISTRO DE ACTIVOS NUEVOS'!$G$5:$G$43,$A7,'REGISTRO DE ACTIVOS NUEVOS'!$L$5:$L$43) | D7: =IFERROR(C7/SUM('REGISTRO DE ACTIVOS NUEVOS'!$L$5:$L$43),0)
A8: Total | B8: =SUM(B5:B7) | C8: =SUM(C5:C7) | D8: =SUM(D5:D7)
A10: Por categoría
A11: Categoría | B11: Activos | C11: Valor total | D11: % del valor
A12: EQUIPOS DE CLIMATIZACION Y REFRIGERACION | B12: =COUNTIF('REGISTRO DE ACTIVOS NUEVOS'!$E$5:$E$43,$A12) | C12: =SUMIF('REGISTRO DE ACTIVOS NUEVOS'!$E$5:$E$43,$A12,'REGISTRO DE ACTIVOS NUEVOS'!$L$5:$L$43) | D12: =IFERROR(C12/SUM('REGISTRO DE ACTIVOS NUEVOS'!$L$5:$L$43),0)
A13: MOBILIARIO | B13: =COUNTIF('REGISTRO DE ACTIVOS NUEVOS'!$E$5:$E$43,$A13) | C13: =SUMIF('REGISTRO DE ACTIVOS NUEVOS'!$E$5:$E$43,$A13,'REGISTRO DE ACTIVOS NUEVOS'!$L$5:$L$43) | D13: =IFERROR(C13/SUM('REGISTRO DE ACTIVOS NUEVOS'!$L$5:$L$43),0)
A14: INFORMATICA | B14: =COUNTIF('REGISTRO DE ACTIVOS NUEVOS'!$E$5:$E$43,$A14) | C14: =SUMIF('REGISTRO DE ACTIVOS NUEVOS'!$E$5:$E$43,$A14,'REGISTRO DE ACTIVOS NUEVOS'!$L$5:$L$43) | D14: =IFERROR(C14/SUM('REGISTRO DE ACTIVOS NUEVOS'!$L$5:$L$43),0)
A15: Total | B15: =SUM(B12:B14) | C15: =SUM(C12:C14) | D15: =SUM(D12:D14)
A17: Por estado
A18: Estado | B18: Activos | C18: Valor total | D18: % del valor
A19: SERVICIO | B19: =COUNTIF('REGISTRO DE ACTIVOS NUEVOS'!$F$5:$F$43,$A19) | C19: =SUMIF('REGISTRO DE ACTIVOS NUEVOS'!$F$5:$F$43,$A19,'REGISTRO DE ACTIVOS NUEVOS'!$L$5:$L$43) | D19: =IFERROR(C19/SUM('REGISTRO DE ACTIVOS NUEVOS'!$L$5:$L$43),0)
A20: MTTO | B20: =COUNTIF('REGISTRO DE ACTIVOS NUEVOS'!$F$5:$F$43,$A20) | C20: =SUMIF('REGISTRO DE ACTIVOS NUEVOS'!$F$5:$F$43,$A20,'REGISTRO DE ACTIVOS NUEVOS'!$L$5:$L$43) | D20: =IFERROR(C20/SUM('REGISTRO DE ACTIVOS NUEVOS'!$L$5:$L$43),0)
A21: BAJA | B21: =COUNTIF('REGISTRO DE ACTIVOS NUEVOS'!$F$5:$F$43,$A21) | C21: =SUMIF('REGISTRO DE ACTIVOS NUEVOS'!$F$5:$F$43,$A21,'REGISTRO DE ACTIVOS NUEVOS'!$L$5:$L$43) | D21: =IFERROR(C21/SUM('REGISTRO DE ACTIVOS NUEVOS'!$L$5:$L$43),0)
A22: Total | B22: =SUM(B19:B21) | C22: =SUM(C19:C21) | D22: =SUM(D19:D21)

Sheet Notas
A1: Notas, supuestos y trazabilidad
A3: Origen del dato
A4: Fuente | B4: Hoja «REGISTRO DE ACTIVOS NUEVOS» de «EJEMPLOS DE EMPRESAS Y AFT (1).xls» (EMPRESA SUCHEL TROPICAL): bloque DIRECCION COMERCIAL, filas 138 a 176 del archivo, códigos DC-01 a DC-39.
A5: Alcance | B5: 39 activos en 3 áreas. El archivo de origen tiene 252 activos en total (DG, DTP, DC, DE, DL); este registro cubre sólo la DIRECCION COMERCIAL.
A6: Rellenado a partir del propio Excel (dato real, sólo desagregado)
A7: DIRECCION | B7: Venía en una única celda combinada que abarcaba las 39 filas. Replicada en cada fila: DIRECCION COMERCIAL.
A8: AREA | B8: Venía sólo en la fila que abre cada bloque. Replicada hacia abajo: DC-01..11 OFICINA DIRECTOR COMERCIAL / DC-12..25 DEPARTAMENTO VENTAS NACIONAL / DC-26..39 DEPARTAMENTO VENTAS INTERNACIONAL.
A9: RESPONSABLE | B9: Mismo criterio que AREA: DIRECTOR COMERCIAL / JEFE DPTO. VENTAS NACIONAL / JEFE DPTO. VENTAS INTERNACIONAL.
A10: Huecos e inconsistencias resueltos
A11: Sin huecos | B11: A diferencia de DIRECCION GENERAL y DIRECCION TECNICO-PRODUCTIVA, este bloque llegó con CATEGORIA y ESTADO completos en las 39 filas: no hubo que asumir ningún valor.
A12: DC-02 | B12: «1 SOFA 3 PERONAS» corregido a «1 SOFA 3 PERSONAS» — la misma errata que traen DG-006 y DTP-06.
A13: BURO vs MESA BURO | B13: Este bloque usa «BURO» / «1 BURO» a secas, mientras DG y DTP usan «MESA BURO/ 4 GAVETAS». Se tomaron como dos bienes distintos (escritorio sin gavetas vs. con 4 gavetas), con modelo y valor distintos. Si en la práctica son el mismo mueble, conviene unificar el nombre antes de aprobar: CORE resuelve el catálogo por nombre.
A14: CREDENZA | B14: Mismo caso: acá dice «1 CREDENZA METALICA» y en DG dice «1 CREDENZA 4 GAVETAS, METALICA». Se trataron como dos referencias distintas (CRD-2P y CRD-4G).
A15: Columnas SIN dato en el origen — valores de EJEMPLO (encabezado en azul)
A16: Advertencia | B16: MARCA, MODELO, SERIE, FECHA COMPRA y VALOR.CLP. están vacías en las 252 filas del Excel de origen. Los valores de estas 5 columnas fueron GENERADOS para entregar el registro completo: son plausibles, no reales. Reemplazar con el acta de recepción / factura antes de aprobar el lote en el CCP.
A17: MARCA / MODELO | B17: Marcas y modelos de mercado chileno coherentes con cada tipo de bien (Rosen, Mica, Ergosillas, Dimeiggs, HP, Epson, Lenovo, LG, Midea, Recco). Los mismos criterios que en los registros de DG y DTP, para que el catálogo quede consistente entre direcciones.
A18: SERIE | B18: Patrón determinista SN-<código sin guión>-<4 dígitos>. No corresponde al número de serie físico del equipo.
A19: FECHA COMPRA | B19: Una fecha por bloque/área, simulando la orden de compra del lote: OFICINA DIRECTOR COMERCIAL 05-2021 / VENTAS NACIONAL 02-2022 / VENTAS INTERNACIONAL 07-2022.
A20: VALOR.CLP. | B20: Valor de reposición referencial en pesos chilenos por tipo de bien. No es valor contable ni valor libro: no incorpora depreciación.
A21: Compatibilidad con el ETL contable de SICSAFT
A22: Hoja y encabezados | B22: El nombre de hoja «REGISTRO DE ACTIVOS NUEVOS» y los 13 encabezados coinciden con herramientas/etl-contable/mapeo/mapeo-ejemplo.json, así que el archivo se procesa tal cual con etl_contable.py.
A23: Fila TOTAL | B23: La fila de totales va sin CODIGO a propósito: el ETL descarta las filas sin codigoPatrimonial, así que no entra al lote como si fuera un activo.
A24: Validación | B24: CATEGORIA, ESTADO, DIRECCION y AREA tienen lista desplegable contra los catálogos de la hoja oculta «Listas», para que una carga manual no invente valores nuevos.
