Workbook

Sheet REGISTRO DE ACTIVOS NUEVOS
A1: CU-PAT — Gestión Patrimonial
A2: EMPRESA SUCHEL TROPICAL · las 5 direcciones · 252 activos · registro consolidado
A4: No. | B4: DIRECCION | C4: CODIGO | D4: NOMBRE AFT | E4: CATEGORIA | F4: ESTADO | G4: AREA | H4: MARCA | I4: MODELO | J4: SERIE | K4: FECHA COMPRA | L4: VALOR.CLP. | M4: RESPONSABLE
A5: 1 | B5: DIRECCION GENERAL | C5: DG-001 | D5: 1 MESA BURO/ 4 GAVETAS | E5: MOBILIARIO | F5: SERVICIO | G5: OFICINA DIRECTOR GENERAL | H5: Rosen | I5: Buro Ejecutivo BR-4G120 | J5: SN-DG001-2186 | K5: 44270 | L5: 189900 | M5: DIRECTOR GENERAL
A6: 2 | B6: DIRECCION GENERAL | C6: DG-002 | D6: 1 SILLA GIRATORIA | E6: MOBILIARIO | F6: SERVICIO | G6: OFICINA DIRECTOR GENERAL | H6: Ergosillas | I6: Pro Ergo 120 | J6: SN-DG002-2323 | K6: 44275 | L6: 109900 | M6: DIRECTOR GENERAL
A7: 3 | B7: DIRECCION GENERAL | C7: DG-003 | D7: 1 PC ESCRITORIO | E7: INFORMATICA | F7: SERVICIO | G7: OFICINA DIRECTOR GENERAL | H7: HP | I7: ProDesk 400 G9 SFF | J7: SN-DG003-2460 | K7: 44280 | L7: 549900 | M7: DIRECTOR GENERAL
A8: 4 | B8: DIRECCION GENERAL | C8: DG-004 | D8: 1 IMPRESORA | E8: INFORMATICA | F8: SERVICIO | G8: OFICINA DIRECTOR GENERAL | H8: Epson | I8: EcoTank L3250 | J8: SN-DG004-2597 | K8: 44270 | L8: 179900 | M8: DIRECTOR GENERAL
A9: 5 | B9: DIRECCION GENERAL | C9: DG-005 | D9: 1 EQUIPO CLIMATIZACION 12000 BTU | E9: EQUIPOS DE CLIMATIZACION Y REFRIGERACION | F9: SERVICIO | G9: OFICINA DIRECTOR GENERAL | H9: Midea | I9: Xtreme Save 12.000 BTU | J9: SN-DG005-2734 | K9: 44275 | L9: 389900 | M9: DIRECTOR GENERAL
A10: 6 | B10: DIRECCION GENERAL | C10: DG-006 | D10: 1 SOFA 3 PERSONAS | E10: MOBILIARIO | F10: SERVICIO | G10: OFICINA DIRECTOR GENERAL | H10: Rosen | I10: Milano 3 Cuerpos | J10: SN-DG006-2871 | K10: 44280 | L10: 429900 | M10: DIRECTOR GENERAL
A11: 7 | B11: DIRECCION GENERAL | C11: DG-007 | D11: BUTACA CON BRAZOS | E11: MOBILIARIO | F11: SERVICIO | G11: OFICINA DIRECTOR GENERAL | H11: Mica | I11: Oslo con Brazos | J11: SN-DG007-3008 | K11: 44270 | L11: 94990 | M11: DIRECTOR GENERAL
A12: 8 | B12: DIRECCION GENERAL | C12: DG-008 | D12: BUTACA CON BRAZOS | E12: MOBILIARIO | F12: SERVICIO | G12: OFICINA DIRECTOR GENERAL | H12: Mica | I12: Oslo con Brazos | J12: SN-DG008-3145 | K12: 44275 | L12: 94990 | M12: DIRECTOR GENERAL
A13: 9 | B13: DIRECCION GENERAL | C13: DG-009 | D13: BUTACA CON BRAZOS | E13: MOBILIARIO | F13: SERVICIO | G13: OFICINA DIRECTOR GENERAL | H13: Mica | I13: Oslo con Brazos | J13: SN-DG009-3282 | K13: 44280 | L13: 94990 | M13: DIRECTOR GENERAL
A14: 10 | B14: DIRECCION GENERAL | C14: DG-010 | D14: 1 TV DIGITAL LG 45" | E14: MOBILIARIO | F14: SERVICIO | G14: OFICINA DIRECTOR GENERAL | H14: LG | I14: 45UR7300 UHD | J14: SN-DG010-3419 | K14: 44270 | L14: 329900 | M14: DIRECTOR GENERAL
A15: 11 | B15: DIRECCION GENERAL | C15: DG-011 | D15: 1 LAPTOP | E15: INFORMATICA | F15: SERVICIO | G15: OFICINA DIRECTOR GENERAL | H15: Lenovo | I15: ThinkPad E14 Gen 5 | J15: SN-DG011-3556 | K15: 44275 | L15: 749900 | M15: DIRECTOR GENERAL
A16: 12 | B16: DIRECCION GENERAL | C16: DG-012 | D16: 1 MESA BURO/ 4 GAVETAS | E16: MOBILIARIO | F16: SERVICIO | G16: OFICINA SECRETARIA EJECUTIVA | H16: Rosen | I16: Buro Ejecutivo BR-4G120 | J16: SN-DG012-3693 | K16: 44367 | L16: 189900 | M16: SECRETARIA EJECUTIVA
... A256: 252 | B256: DIRECCION LOGISTICA | C256: DL-27 | D256: 1 VENTILADOR | E256: EQUIPOS DE CLIMATIZACION Y REFRIGERACION | F256: SERVICIO | G256: ALMACEN PERFUMERIA | H256: Recco | I256: RVP-45PM Pedestal | J256: SN-DL27-5748 | K256: 44883 | L256: 39990 | M256: JEFE ALMACEN PERFUMERIA
A257: TOTAL | D257: =COUNTA(C5:C256)&" activos en "&SUMPRODUCT(1/COUNTIF(B5:B256,B5:B256))&" direcciones" | L257: =SUM(L5:L256)

Sheet Listas
A1: CATEGORIA | B1: ESTADO | C1: DIRECCION | D1: AREA
A2: MOBILIARIO | B2: SERVICIO | C2: DIRECCION GENERAL | D2: OFICINA DIRECTOR GENERAL
A3: INFORMATICA | B3: MTTO | C3: DIRECCION TECNICO-PRODUCTIVA | D3: OFICINA SECRETARIA EJECUTIVA
A4: EQUIPOS DE CLIMATIZACION Y REFRIGERACION | B4: BAJA | C4: DIRECCION COMERCIAL | D4: SALON REUNIONES
A5: ELECTRODOMESTICOS | C5: DIRECCION ECONOMIA | D5: JURIDICO
A6: TECNOLOGIA | C6: DIRECCION LOGISTICA | D6: PANTRY
A7: TRANSPORTE | D7: OFICINA DIRECTOR TECN.// PRODUCT.
D8: DEPARTAMENTO TECNICO
D9: DEPARTAMENTO PRODUCC.
D10: PLANTA JABONERIA
D11: PLANTA PERFUMERIA
D12: OFICINA DIRECTOR COMERCIAL
D13: DEPARTAMENTO VENTAS NACIONAL
D14: DEPARTAMENTO VENTAS INTERNACIONAL
D15: OFICINA DIRECTOR ECONOMIA
D16: DEPARTAMENTO CONTABILIDAD
D17: DEPARTAMENTO FINANZAS
D18: OFICINA DIRECTOR LOGISTICA
D19: DEPARTAMENTO TRANSPORTE
... D21: ALMACEN PERFUMERIA

Sheet Resumen
A1: Resumen consolidado — 252 activos, 5 direcciones
A3: Por dirección
A4: Dirección | B4: Activos | C4: Valor total | D4: % del valor
A5: DIRECCION GENERAL | B5: =COUNTIF('REGISTRO DE ACTIVOS NUEVOS'!$B$5:$B$256,$A5) | C5: =SUMIF('REGISTRO DE ACTIVOS NUEVOS'!$B$5:$B$256,$A5,'REGISTRO DE ACTIVOS NUEVOS'!$L$5:$L$256) | D5: =IFERROR(C5/SUM('REGISTRO DE ACTIVOS NUEVOS'!$L$5:$L$256),0)
A6: DIRECCION TECNICO-PRODUCTIVA | B6: =COUNTIF('REGISTRO DE ACTIVOS NUEVOS'!$B$5:$B$256,$A6) | C6: =SUMIF('REGISTRO DE ACTIVOS NUEVOS'!$B$5:$B$256,$A6,'REGISTRO DE ACTIVOS NUEVOS'!$L$5:$L$256) | D6: =IFERROR(C6/SUM('REGISTRO DE ACTIVOS NUEVOS'!$L$5:$L$256),0)
A7: DIRECCION COMERCIAL | B7: =COUNTIF('REGISTRO DE ACTIVOS NUEVOS'!$B$5:$B$256,$A7) | C7: =SUMIF('REGISTRO DE ACTIVOS NUEVOS'!$B$5:$B$256,$A7,'REGISTRO DE ACTIVOS NUEVOS'!$L$5:$L$256) | D7: =IFERROR(C7/SUM('REGISTRO DE ACTIVOS NUEVOS'!$L$5:$L$256),0)
A8: DIRECCION ECONOMIA | B8: =COUNTIF('REGISTRO DE ACTIVOS NUEVOS'!$B$5:$B$256,$A8) | C8: =SUMIF('REGISTRO DE ACTIVOS NUEVOS'!$B$5:$B$256,$A8,'REGISTRO DE ACTIVOS NUEVOS'!$L$5:$L$256) | D8: =IFERROR(C8/SUM('REGISTRO DE ACTIVOS NUEVOS'!$L$5:$L$256),0)
A9: DIRECCION LOGISTICA | B9: =COUNTIF('REGISTRO DE ACTIVOS NUEVOS'!$B$5:$B$256,$A9) | C9: =SUMIF('REGISTRO DE ACTIVOS NUEVOS'!$B$5:$B$256,$A9,'REGISTRO DE ACTIVOS NUEVOS'!$L$5:$L$256) | D9: =IFERROR(C9/SUM('REGISTRO DE ACTIVOS NUEVOS'!$L$5:$L$256),0)
A10: Total | B10: =SUM(B5:B9) | C10: =SUM(C5:C9) | D10: =SUM(D5:D9)
A12: Por categoría
A13: Categoría | B13: Activos | C13: Valor total | D13: % del valor
A14: MOBILIARIO | B14: =COUNTIF('REGISTRO DE ACTIVOS NUEVOS'!$E$5:$E$256,$A14) | C14: =SUMIF('REGISTRO DE ACTIVOS NUEVOS'!$E$5:$E$256,$A14,'REGISTRO DE ACTIVOS NUEVOS'!$L$5:$L$256) | D14: =IFERROR(C14/SUM('REGISTRO DE ACTIVOS NUEVOS'!$L$5:$L$256),0)
A15: INFORMATICA | B15: =COUNTIF('REGISTRO DE ACTIVOS NUEVOS'!$E$5:$E$256,$A15) | C15: =SUMIF('REGISTRO DE ACTIVOS NUEVOS'!$E$5:$E$256,$A15,'REGISTRO DE ACTIVOS NUEVOS'!$L$5:$L$256) | D15: =IFERROR(C15/SUM('REGISTRO DE ACTIVOS NUEVOS'!$L$5:$L$256),0)
A16: EQUIPOS DE CLIMATIZACION Y REFRIGERACION | B16: =COUNTIF('REGISTRO DE ACTIVOS NUEVOS'!$E$5:$E$256,$A16) | C16: =SUMIF('REGISTRO DE ACTIVOS NUEVOS'!$E$5:$E$256,$A16,'REGISTRO DE ACTIVOS NUEVOS'!$L$5:$L$256) | D16: =IFERROR(C16/SUM('REGISTRO DE ACTIVOS NUEVOS'!$L$5:$L$256),0)
A17: ELECTRODOMESTICOS | B17: =COUNTIF('REGISTRO DE ACTIVOS NUEVOS'!$E$5:$E$256,$A17) | C17: =SUMIF('REGISTRO DE ACTIVOS NUEVOS'!$E$5:$E$256,$A17,'REGISTRO DE ACTIVOS NUEVOS'!$L$5:$L$256) | D17: =IFERROR(C17/SUM('REGISTRO DE ACTIVOS NUEVOS'!$L$5:$L$256),0)
A18: TECNOLOGIA | B18: =COUNTIF('REGISTRO DE ACTIVOS NUEVOS'!$E$5:$E$256,$A18) | C18: =SUMIF('REGISTRO DE ACTIVOS NUEVOS'!$E$5:$E$256,$A18,'REGISTRO DE ACTIVOS NUEVOS'!$L$5:$L$256) | D18: =IFERROR(C18/SUM('REGISTRO DE ACTIVOS NUEVOS'!$L$5:$L$256),0)
A19: TRANSPORTE | B19: =COUNTIF('REGISTRO DE ACTIVOS NUEVOS'!$E$5:$E$256,$A19) | C19: =SUMIF('REGISTRO DE ACTIVOS NUEVOS'!$E$5:$E$256,$A19,'REGISTRO DE ACTIVOS NUEVOS'!$L$5:$L$256) | D19: =IFERROR(C19/SUM('REGISTRO DE ACTIVOS NUEVOS'!$L$5:$L$256),0)
A20: Total | B20: =SUM(B14:B19) | C20: =SUM(C14:C19) | D20: =SUM(D14:D19)
A22: Por estado
A23: Estado | B23: Activos | C23: Valor total | D23: % del valor
A24: SERVICIO | B24: =COUNTIF('REGISTRO DE ACTIVOS NUEVOS'!$F$5:$F$256,$A24) | C24: =SUMIF('REGISTRO DE ACTIVOS NUEVOS'!$F$5:$F$256,$A24,'REGISTRO DE ACTIVOS NUEVOS'!$L$5:$L$256) | D24: =IFERROR(C24/SUM('REGISTRO DE ACTIVOS NUEVOS'!$L$5:$L$256),0)
A25: MTTO | B25: =COUNTIF('REGISTRO DE ACTIVOS NUEVOS'!$F$5:$F$256,$A25) | C25: =SUMIF('REGISTRO DE ACTIVOS NUEVOS'!$F$5:$F$256,$A25,'REGISTRO DE ACTIVOS NUEVOS'!$L$5:$L$256) | D25: =IFERROR(C25/SUM('REGISTRO DE ACTIVOS NUEVOS'!$L$5:$L$256),0)
A26: BAJA | B26: =COUNTIF('REGISTRO DE ACTIVOS NUEVOS'!$F$5:$F$256,$A26) | C26: =SUMIF('REGISTRO DE ACTIVOS NUEVOS'!$F$5:$F$256,$A26,'REGISTRO DE ACTIVOS NUEVOS'!$L$5:$L$256) | D26: =IFERROR(C26/SUM('REGISTRO DE ACTIVOS NUEVOS'!$L$5:$L$256),0)
A27: Total | B27: =SUM(B24:B26) | C27: =SUM(C24:C26) | D27: =SUM(D24:D26)
A29: Por área
A30: Área | B30: Activos | C30: Valor total | D30: % del valor
A31: OFICINA DIRECTOR GENERAL | B31: =COUNTIF('REGISTRO DE ACTIVOS NUEVOS'!$G$5:$G$256,$A31) | C31: =SUMIF('REGISTRO DE ACTIVOS NUEVOS'!$G$5:$G$256,$A31,'REGISTRO DE ACTIVOS NUEVOS'!$L$5:$L$256) | D31: =IFERROR(C31/SUM('REGISTRO DE ACTIVOS NUEVOS'!$L$5:$L$256),0)
A32: OFICINA SECRETARIA EJECUTIVA | B32: =COUNTIF('REGISTRO DE ACTIVOS NUEVOS'!$G$5:$G$256,$A32) | C32: =SUMIF('REGISTRO DE ACTIVOS NUEVOS'!$G$5:$G$256,$A32,'REGISTRO DE ACTIVOS NUEVOS'!$L$5:$L$256) | D32: =IFERROR(C32/SUM('REGISTRO DE ACTIVOS NUEVOS'!$L$5:$L$256),0)
A33: SALON REUNIONES | B33: =COUNTIF('REGISTRO DE ACTIVOS NUEVOS'!$G$5:$G$256,$A33) | C33: =SUMIF('REGISTRO DE ACTIVOS NUEVOS'!$G$5:$G$256,$A33,'REGISTRO DE ACTIVOS NUEVOS'!$L$5:$L$256) | D33: =IFERROR(C33/SUM('REGISTRO DE ACTIVOS NUEVOS'!$L$5:$L$256),0)
A34: JURIDICO | B34: =COUNTIF('REGISTRO DE ACTIVOS NUEVOS'!$G$5:$G$256,$A34) | C34: =SUMIF('REGISTRO DE ACTIVOS NUEVOS'!$G$5:$G$256,$A34,'REGISTRO DE ACTIVOS NUEVOS'!$L$5:$L$256) | D34: =IFERROR(C34/SUM('REGISTRO DE ACTIVOS NUEVOS'!$L$5:$L$256),0)
A35: PANTRY | B35: =COUNTIF('REGISTRO DE ACTIVOS NUEVOS'!$G$5:$G$256,$A35) | C35: =SUMIF('REGISTRO DE ACTIVOS NUEVOS'!$G$5:$G$256,$A35,'REGISTRO DE ACTIVOS NUEVOS'!$L$5:$L$256) | D35: =IFERROR(C35/SUM('REGISTRO DE ACTIVOS NUEVOS'!$L$5:$L$256),0)
A36: OFICINA DIRECTOR TECN.// PRODUCT. | B36: =COUNTIF('REGISTRO DE ACTIVOS NUEVOS'!$G$5:$G$256,$A36) | C36: =SUMIF('REGISTRO DE ACTIVOS NUEVOS'!$G$5:$G$256,$A36,'REGISTRO DE ACTIVOS NUEVOS'!$L$5:$L$256) | D36: =IFERROR(C36/SUM('REGISTRO DE ACTIVOS NUEVOS'!$L$5:$L$256),0)
A37: DEPARTAMENTO TECNICO | B37: =COUNTIF('REGISTRO DE ACTIVOS NUEVOS'!$G$5:$G$256,$A37) | C37: =SUMIF('REGISTRO DE ACTIVOS NUEVOS'!$G$5:$G$256,$A37,'REGISTRO DE ACTIVOS NUEVOS'!$L$5:$L$256) | D37: =IFERROR(C37/SUM('REGISTRO DE ACTIVOS NUEVOS'!$L$5:$L$256),0)
A38: DEPARTAMENTO PRODUCC. | B38: =COUNTIF('REGISTRO DE ACTIVOS NUEVOS'!$G$5:$G$256,$A38) | C38: =SUMIF('REGISTRO DE ACTIVOS NUEVOS'!$G$5:$G$256,$A38,'REGISTRO DE ACTIVOS NUEVOS'!$L$5:$L$256) | D38: =IFERROR(C38/SUM('REGISTRO DE ACTIVOS NUEVOS'!$L$5:$L$256),0)
A39: PLANTA JABONERIA | B39: =COUNTIF('REGISTRO DE ACTIVOS NUEVOS'!$G$5:$G$256,$A39) | C39: =SUMIF('REGISTRO DE ACTIVOS NUEVOS'!$G$5:$G$256,$A39,'REGISTRO DE ACTIVOS NUEVOS'!$L$5:$L$256) | D39: =IFERROR(C39/SUM('REGISTRO DE ACTIVOS NUEVOS'!$L$5:$L$256),0)
A40: PLANTA PERFUMERIA | B40: =COUNTIF('REGISTRO DE ACTIVOS NUEVOS'!$G$5:$G$256,$A40) | C40: =SUMIF('REGISTRO DE ACTIVOS NUEVOS'!$G$5:$G$256,$A40,'REGISTRO DE ACTIVOS NUEVOS'!$L$5:$L$256) | D40: =IFERROR(C40/SUM('REGISTRO DE ACTIVOS NUEVOS'!$L$5:$L$256),0)
A41: OFICINA DIRECTOR COMERCIAL | B41: =COUNTIF('REGISTRO DE ACTIVOS NUEVOS'!$G$5:$G$256,$A41) | C41: =SUMIF('REGISTRO DE ACTIVOS NUEVOS'!$G$5:$G$256,$A41,'REGISTRO DE ACTIVOS NUEVOS'!$L$5:$L$256) | D41: =IFERROR(C41/SUM('REGISTRO DE ACTIVOS NUEVOS'!$L$5:$L$256),0)
A42: DEPARTAMENTO VENTAS NACIONAL | B42: =COUNTIF('REGISTRO DE ACTIVOS NUEVOS'!$G$5:$G$256,$A42) | C42: =SUMIF('REGISTRO DE ACTIVOS NUEVOS'!$G$5:$G$256,$A42,'REGISTRO DE ACTIVOS NUEVOS'!$L$5:$L$256) | D42: =IFERROR(C42/SUM('REGISTRO DE ACTIVOS NUEVOS'!$L$5:$L$256),0)
... A50: ALMACEN PERFUMERIA | B50: =COUNTIF('REGISTRO DE ACTIVOS NUEVOS'!$G$5:$G$256,$A50) | C50: =SUMIF('REGISTRO DE ACTIVOS NUEVOS'!$G$5:$G$256,$A50,'REGISTRO DE ACTIVOS NUEVOS'!$L$5:$L$256) | D50: =IFERROR(C50/SUM('REGISTRO DE ACTIVOS NUEVOS'!$L$5:$L$256),0)
A51: Total | B51: =SUM(B31:B50) | C51: =SUM(C31:C50) | D51: =SUM(D31:D50)

Sheet Notas
A1: Notas, supuestos y trazabilidad — consolidado
A3: Qué es este archivo
A4: Contenido | B4: Los 252 activos de EMPRESA SUCHEL TROPICAL en una sola hoja: DIRECCION GENERAL (60) + TECNICO-PRODUCTIVA (77) + COMERCIAL (39) + ECONOMIA (49) + LOGISTICA (27). La columna No. reproduce la numeración correlativa 1..252 del archivo de origen.
A5: Fuente | B5: Hoja «REGISTRO DE ACTIVOS NUEVOS» de «EJEMPLOS DE EMPRESAS Y AFT (1).xls». Este consolidado se armó leyendo los cinco registros por dirección ya entregados, no re-procesando el .xls, así que es exactamente la unión de esos cinco archivos.
A6: Cómo leerlo | B6: Una línea azul gruesa separa cada dirección. El autofiltro de la fila de encabezados permite aislar una dirección, un área o un estado sin tocar los archivos individuales.
A7: Código de colores
A8: Encabezado azul | B8: MARCA, MODELO, SERIE, FECHA COMPRA y VALOR.CLP.: columnas VACÍAS en las 252 filas del origen. Todo lo que ves ahí fue GENERADO — plausible, no real. Reemplazar con el acta de recepción / factura antes de aprobar.
A9: Celda ámbar | B9: Valor DEDUCIDO, no venía en el origen. Son las 27 filas de LOGISTICA (CATEGORIA y ESTADO vacías en las 27), más DG-042, DG-043, DG-048, DTP-28, DTP-55, DTP-57 y DTP-61. En la columna ESTADO el ámbar también marca MTTO y el rojo marca BAJA, que sí son dato real del origen.
A10: Celda roja | B10: ESTADO = BAJA. Dato real del origen: DTP-34, DTP-46 y DTP-76.
A11: Qué venía completo y qué no, por dirección
A12: GENERAL (60) | B12: 3 filas sin ESTADO (DG-042, DG-043, DG-048) y 1 sin CATEGORIA (DG-048). DG-016 venía como «CLIMATIZACION Y REFRIGERACION» y se normalizó a «EQUIPOS DE CLIMATIZACION Y REFRIGERACION».
A13: TECNICO-PROD. (77) | B13: 4 filas sin ESTADO (DTP-28, DTP-55, DTP-57, DTP-61), completadas con SERVICIO. DTP-39 venía como «4 LINEAS DE JABONERIA» (4 máquinas bajo un código) y quedó corregido — ver abajo.
A14: LOGISTICA: dirección | B14: En la hoja de registro NO existe la celda «DIRECCION LOGISTICA»: la columna viene vacía en las 27 filas. Acá figura completa porque la hoja «EMPRESA SUCHEL TROPICAL» del mismo archivo sí la lista (fila 73). Si en cambio se carga el .xls original tal cual, el relleno hacia abajo del ETL arrastra DIRECCION ECONOMIA a esos 27 activos y quedan en la dirección equivocada, sin que nada avise.
A15: COMERCIAL (39) | B15: Completo: CATEGORIA y ESTADO en las 39 filas.
A16: ECONOMIA (49) | B16: Completo, y el único bloque enteramente en SERVICIO. Contabilidad y Finanzas tienen composición idéntica (19 activos cada uno).
A17: LOGISTICA (27) | B17: El bloque con más deducción: CATEGORIA y ESTADO vacías en las 27 filas (0 de 27 en ambas, verificado sobre el .xls). La categoría se dedujo por tipo de bien según cómo está catalogado en las otras direcciones; el estado se asumió SERVICIO en las 27.
A18: Nomenclatura — lo más importante a resolver antes de aprobar
A19: Advertencia | B19: CORE resuelve el catálogo por NOMBRE EXACTO, y el archivo nombra el mismo bien de varias formas: «1 IMPRESORA»/«IMPRESORA», «1 BURO»/«BURO», «MESA BURO/ 4 GAVETAS», «1 SILLA GIRATORIA»/«SILLA GIRATORIA», «1 CREDENZA METALICA»/«CREDENZAS METALICAS»/«1 CREDENZA 4 GAVETAS, METALICA», «1 EQUIPO CLIMATIZACION 12000 BTU»/«1 EQUIPO CLIMA 12000 BTU» y «1 SOFA 3 PERONAS»/«1 SOFA 3 PLAZAS». Tal como están, cada variante crea una entrada de catálogo distinta para el mismo bien. Este consolidado es el mejor lugar para unificarlas, porque acá se ven las cinco direcciones juntas.
A20: DTP-39 corregido | B20: El origen registraba «4 LINEAS DE JABONERIA»: 4 máquinas bajo un solo código, o sea 4 equipos compartiendo una etiqueta. Confirmado que la planta tiene 4 líneas en total (el «4» era el encabezado del grupo), DTP-39 quedó como «LINEA DE JABONERIA» — la línea 1 — y DTP-40, DTP-41 y DTP-42 son la 2, 3 y 4. Su valor bajó de 4 × línea a 1 × línea. Es el único NOMBRE AFT que difiere del texto literal del .xls por algo que no es una errata de tipeo.
A21: Erratas corregidas | B21: «1MESA»→«1 MESA» (DG-012, DG-020), espacios sobrantes al inicio (DG-001, DG-012, DG-020, DTP-01), «3 PERONAS»→«3 PERSONAS» (DG-006, DTP-06, DC-02, DE-02) y el espacio inicial de « ALMACEN JABONERIA» / « ALMACEN PERFUMERIA».
A22: Nombres respetados | B22: «OFICINA DIRECTOR TECN.// PRODUCT.», «DIRECTOR TECN. // PRODUCT.» y «DIRECTOR TRANSPORTE» (en vez de «JEFE DPTO. TRANSPORTE») se dejaron tal cual: CORE resuelve área y responsable por nombre exacto, así que normalizarlos crearía registros duplicados.
A23: Sobre los valores en pesos
A24: Advertencia | B24: El total del registro está dominado por las 13 líneas de producción de TECNOLOGIA (~96% del valor de esa dirección), y todas esas cifras las generé yo. Cualquier conclusión que salga hoy del Resumen — peso relativo de una dirección, ranking de áreas — está determinada por números inventados. Reemplazar primero las líneas de producción, los chillers, los compresores y el montacarga; el equipamiento de oficina casi no mueve la aguja.
A25: VALOR.CLP. | B25: Valor de reposición referencial por tipo de bien. No es valor contable ni valor libro: no incorpora depreciación.
A26: Compatibilidad con el ETL contable de SICSAFT
A27: Hoja y encabezados | B27: El nombre de hoja «REGISTRO DE ACTIVOS NUEVOS» y los 13 encabezados coinciden con herramientas/etl-contable/mapeo/mapeo-ejemplo.json: el archivo se procesa tal cual con etl_contable.py y produce un lote de 252 filas.
A28: Fila TOTAL | B28: Va sin CODIGO a propósito: el ETL descarta las filas sin codigoPatrimonial, así que no entra al lote como si fuera un activo.
A29: Un lote o cinco | B29: Este consolidado sirve para revisar y para cargar todo de una. Si preferís aprobar dirección por dirección en el CCP, los cinco archivos individuales generan cinco lotes separados con el mismo contenido.
